soupx/__init__.py
soupx/core.py
soupx/correction.py
soupx/estimation.py
soupx/scanpy_integration.py
soupx/utils.py
soupx_python-0.3.0.dist-info/METADATA
soupx_python-0.3.0.dist-info/WHEEL
soupx_python-0.3.0.dist-info/top_level.txt
soupx_python-0.3.0.dist-info/RECORD
