Metadata-Version: 2.4
Name: soupx-python
Version: 0.3.0
Summary: Python implementation of SoupX for removing ambient RNA contamination from droplet-based single-cell RNA sequencing data
Author-email: Nicolas Ruffini <nicolas.ruffini@posteo.de>
Maintainer-email: Nicolas Ruffini <nicolas.ruffini@posteo.de>
License: GPL-2.0
Project-URL: Homepage, https://github.com/NiRuff/soupx-python
Project-URL: Repository, https://github.com/NiRuff/soupx-python
Project-URL: Bug Tracker, https://github.com/NiRuff/soupx-python/issues
Keywords: single-cell,RNA-seq,bioinformatics,decontamination,ambient-RNA,soupx
Classifier: Development Status :: 4 - Beta
Classifier: Intended Audience :: Science/Research
Classifier: Topic :: Scientific/Engineering :: Bio-Informatics
Classifier: License :: OSI Approved :: GNU General Public License v2 (GPLv2)
Classifier: Programming Language :: Python :: 3
Classifier: Programming Language :: Python :: 3.8
Classifier: Programming Language :: Python :: 3.9
Classifier: Programming Language :: Python :: 3.10
Classifier: Programming Language :: Python :: 3.11
Classifier: Programming Language :: Python :: 3.12
Requires-Python: >=3.8
Requires-Dist: numpy>=1.20.0
Requires-Dist: pandas>=1.3.0
Requires-Dist: scipy>=1.7.0
Requires-Dist: statsmodels>=0.12.0
Requires-Dist: scanpy>=1.8.0
